{
  "$schema": "https://developer.microsoft.com/json-schemas/fabric/item/report/definition/visualContainer/2.6.0/schema.json",
  "name": "1d37da28770d23e7b75f",
  "position": {
    "x": 10,
    "y": 0,
    "z": 0,
    "height": 65,
    "width": 280,
    "tabOrder": 0
  },
  "visual": {
    "visualType": "slicer",
    "query": {
      "queryState": {
        "Values": {
          "projections": [
            {
              "field": {
                "Column": {
                  "Expression": {
                    "SourceRef": {
                      "Entity": "DimEmployee"
                    }
                  },
                  "Property": "FullName"
                }
              },
              "queryRef": "DimEmployee.FullName",
              "nativeQueryRef": "FullName",
              "active": true
            }
          ]
        }
      }
    },
    "objects": {
      "data": [
        {
          "properties": {
            "mode": {
              "expr": {
                "Literal": {
                  "Value": "'Dropdown'"
                }
              }
            }
          }
        }
      ],
      "selection": [
        {
          "properties": {
            "strictSingleSelect": {
              "expr": {
                "Literal": {
                  "Value": "true"
                }
              }
            }
          }
        }
      ],
      "general": [
        {
          "properties": {
            "orientation": {
              "expr": {
                "Literal": {
                  "Value": "0D"
                }
              }
            },
            "filter": {
              "filter": {
                "Version": 2,
                "From": [
                  {
                    "Name": "d",
                    "Entity": "DimEmployee",
                    "Type": 0
                  }
                ],
                "Where": [
                  {
                    "Condition": {
                      "In": {
                        "Expressions": [
                          {
                            "Column": {
                              "Expression": {
                                "SourceRef": {
                                  "Source": "d"
                                }
                              },
                              "Property": "FullName"
                            }
                          }
                        ],
                        "Values": [
                          [
                            {
                              "Literal": {
                                "Value": "'Estelle Chung'"
                              }
                            }
                          ]
                        ]
                      }
                    }
                  }
                ]
              }
            },
            "selfFilterEnabled": {
              "expr": {
                "Literal": {
                  "Value": "true"
                }
              }
            },
            "selfFilter": {
              "filter": {
                "Version": 2,
                "From": [
                  {
                    "Name": "d",
                    "Entity": "DimEmployee",
                    "Type": 0
                  }
                ],
                "Where": [
                  {
                    "Condition": {
                      "Contains": {
                        "Left": {
                          "Column": {
                            "Expression": {
                              "SourceRef": {
                                "Source": "d"
                              }
                            },
                            "Property": "FullName"
                          }
                        },
                        "Right": {
                          "Literal": {
                            "Value": "'estell'"
                          }
                        }
                      }
                    },
                    "Annotations": {
                      "PowerBI.MParameterBehavior": 1
                    }
                  }
                ]
              }
            }
          }
        }
      ],
      "header": [
        {
          "properties": {
            "text": {
              "expr": {
                "Literal": {
                  "Value": "'Select employee'"
                }
              }
            }
          }
        }
      ]
    },
    "visualContainerObjects": {
      "title": [
        {
          "properties": {
            "show": {
              "expr": {
                "Literal": {
                  "Value": "false"
                }
              }
            },
            "text": {
              "expr": {
                "Literal": {
                  "Value": "'Select employee'"
                }
              }
            }
          }
        }
      ]
    },
    "drillFilterOtherVisuals": true
  },
  "filterConfig": {
    "filters": [
      {
        "name": "75c3309f1144166576d7",
        "field": {
          "Column": {
            "Expression": {
              "SourceRef": {
                "Entity": "DimEmployee"
              }
            },
            "Property": "FullName"
          }
        },
        "type": "Categorical"
      }
    ]
  }
}